citcall/__init__.py
citcall/citcall.py
citcall/exception.py
citcall_devel-0.4.dist-info/LICENSE.txt
citcall_devel-0.4.dist-info/METADATA
citcall_devel-0.4.dist-info/WHEEL
citcall_devel-0.4.dist-info/top_level.txt
citcall_devel-0.4.dist-info/RECORD
