Metadata-Version: 2.1
Name: citcall-devel
Version: 0.4
Summary: Citcall REST API for Python
Home-page: https://github.com/citcall/citcall-python
Author: Citcall
Author-email: devel@citcall.com
License: UNKNOWN
Platform: UNKNOWN
Classifier: Programming Language :: Python :: 3
Classifier: License :: OSI Approved :: MIT License
Classifier: Operating System :: OS Independent
Requires-Python: >=3.5
License-File: LICENSE.txt
